package/__init__.py
package/common.py
package/roblang.py
package/socketfunc.py
package/visionfunc.py
vision_kais-0.0.1.dist-info/METADATA
vision_kais-0.0.1.dist-info/WHEEL
vision_kais-0.0.1.dist-info/top_level.txt
vision_kais-0.0.1.dist-info/RECORD
