Metadata-Version: 2.1
Name: vision-kais
Version: 0.0.1
Summary: vision function written by kais
Home-page: UNKNOWN
Author: misil han
Author-email: coko980715@gmail.com
License: UNKNOWN
Keywords: kais,vision
Platform: UNKNOWN
Classifier: Programming Language :: Python :: 3.8
Requires-Python: >=3.6
Requires-Dist: socket
Requires-Dist: requests
